sfst_transduce.cp314-win32.pyd
sfst_transduce/__init__.pyi
sfst_transduce/py.typed
sfst_transduce-1.3.1.dist-info/LICENSE
sfst_transduce-1.3.1.dist-info/METADATA
sfst_transduce-1.3.1.dist-info/WHEEL
sfst_transduce-1.3.1.dist-info/top_level.txt
sfst_transduce-1.3.1.dist-info/RECORD
