Metadata-Version: 2.1
Name: sfst-transduce
Version: 1.3.1
Summary: Python bindings for SFST focusing on transducer usage
Author-email: Gregor Middell <gregor.middell@bbaw.de>
Project-URL: Homepage, https://github.com/zentrum-lexikographie/sfst-transduce
Project-URL: Repository, https://github.com/zentrum-lexikographie/sfst-transduce.git
Keywords: Finite-state Transducer,Morphological Analysis,Natural Language Processing,NLP,SFST
Classifier: Development Status :: 5 - Production/Stable
Classifier: Intended Audience :: Developers
Classifier: Intended Audience :: Science/Research
Classifier: License :: OSI Approved :: GNU General Public License v2 (GPLv2)
Classifier: Operating System :: MacOS
Classifier: Operating System :: Microsoft :: Windows
Classifier: Operating System :: POSIX :: Linux
Classifier: Programming Language :: C++
Classifier: Programming Language :: Python
Classifier: Programming Language :: Python :: 3.8
Classifier: Programming Language :: Python :: 3.9
Classifier: Programming Language :: Python :: 3.10
Classifier: Programming Language :: Python :: 3.11
Classifier: Programming Language :: Python :: 3.12
Classifier: Programming Language :: Python :: 3.13
Classifier: Programming Language :: Python :: Implementation
Classifier: Programming Language :: Python :: Implementation :: CPython
Classifier: Programming Language :: Python :: Implementation :: PyPy
Classifier: Topic :: Education
Classifier: Topic :: Scientific/Engineering
Classifier: Topic :: Text Processing :: Linguistic
Requires-Python: >=3.8
License-File: LICENSE
